sprak/__init__.py
sprak/sprite_packer.py
sprak/models/__init__.py
sprak/models/atlas.py
sprak/models/frame.py
sprak/models/rect.py
sprak/utilities/__init__.py
sprak/utilities/ffmpeg_utils.py
sprak-1.0.0.post1.dist-info/METADATA
sprak-1.0.0.post1.dist-info/WHEEL
sprak-1.0.0.post1.dist-info/licenses/LICENSE
sprak-1.0.0.post1.dist-info/RECORD
