Metadata-Version: 2.3
Name: sprak
Version: 1.0.0.post1
Summary: A Python module for packing sprites into a texture atlas.
Project-URL: Homepage, https://github.com/kennedy0/sprak
Author: Andrew Kennedy
License-File: LICENSE
Keywords: aseprite,game development,pygame
Classifier: License :: OSI Approved :: MIT License
Classifier: Operating System :: OS Independent
Classifier: Programming Language :: Python :: 3
Requires-Python: >=3.12
Requires-Dist: aseprite-reader
Requires-Dist: pillow
